brikeda_client/__init__.py
brikeda_client/brikeda.py
brikeda_client/test.py
brikeda_client-0.0.4.dist-info/LICENSE
brikeda_client-0.0.4.dist-info/METADATA
brikeda_client-0.0.4.dist-info/WHEEL
brikeda_client-0.0.4.dist-info/top_level.txt
brikeda_client-0.0.4.dist-info/RECORD
