Metadata-Version: 2.1
Name: brikeda-client
Version: 0.0.4
Summary: For Computer Vision, Speech Generation, and Controlling waveshare Motor Controller
Home-page: https://github.com/markBosley/brikeda_client
Author: Mark Bosley
Author-email: mark.bosley@brikeda.com
Classifier: Programming Language :: Python :: 3
Classifier: License :: OSI Approved :: MIT License
Classifier: Operating System :: OS Independent
Requires-Python: >=3.7
License-File: LICENSE
Requires-Dist: requests
Requires-Dist: urllib3
